kport.py
kport-3.1.0.dist-info/licenses/LICENSE
kport-3.1.0.dist-info/METADATA
kport-3.1.0.dist-info/WHEEL
kport-3.1.0.dist-info/entry_points.txt
kport-3.1.0.dist-info/top_level.txt
kport-3.1.0.dist-info/RECORD
